simplegame/__init__.py
simplegame/sg.py
simplegame-0.0.11.dist-info/METADATA
simplegame-0.0.11.dist-info/WHEEL
simplegame-0.0.11.dist-info/top_level.txt
simplegame-0.0.11.dist-info/RECORD
