Metadata-Version: 2.1
Name: simplegame
Version: 0.0.11
Summary: Package for creating simple games
Home-page: https://github.com/szotms/simplegame
Author: Michal Szot
Author-email: szot.net@gmail.com
License: MIT
Requires-Dist: Pillow >=11.0.0
Requires-Dist: pygame >=2.6.1
